autosignin/__init__.py
autosignin/test1.py
autosignup/__init__.py
autosignup/test1.py
signin/__init__.py
signin/test1.py
signup/__init__.py
signup/test1.py
signin-0.0.2.dist-info/LICENSE.txt
signin-0.0.2.dist-info/METADATA
signin-0.0.2.dist-info/WHEEL
signin-0.0.2.dist-info/entry_points.txt
signin-0.0.2.dist-info/top_level.txt
signin-0.0.2.dist-info/RECORD
