Metadata-Version: 2.1
Name: signin
Version: 0.0.2
Summary: Auto sign in.
Home-page: https://github.com/LoveNishimiyaShouko/signin
Author: LoveNishimiyaShouko
Author-email: LoveNishimiyaShouko@LoveNishimiyaShouko.LoveNishimiyaShouko
License: AGPLv3
Project-URL: Documentation, https://github.com/LoveNishimiyaShouko/signin/tree/main/docs
Project-URL: Source, https://github.com/LoveNishimiyaShouko/signin/tree/main/code
Keywords: auto,sign in,auto sign in
Platform: UNKNOWN
Classifier: Development Status :: 5 - Production/Stable
Classifier: License :: OSI Approved :: GNU Affero General Public License v3 or later (AGPLv3+)
Classifier: Operating System :: OS Independent
Classifier: Programming Language :: Python
Requires-Python: >=3
Requires-Dist: requests
